{
  "$schema": "https://json-schema.org/draft/2020-12/schema",
  "$id": "feed_view.schema.json",
  "type": "object",
  "description": "FeedView entity for feeds import.",
  "required": ["view_id"],
  "properties": {
    "view_id": { "type": "string", "minLength": 1 },
    "app_pk": { "type": "integer" },
    "activity_selectors": { "type": "array" },
    "ranking": { "type": "object", "additionalProperties": true },
    "aggregation": { "type": "object", "additionalProperties": true },
    "aggregation_version": { "type": "integer" },
    "last_feed_get_at": { "type": ["string", "null"], "format": "date-time" },
    "created_at": { "type": "string", "format": "date-time" }
  }
}
