{
    "$schema": "https://json-schema.org/draft/2020-12/schema",
    "$id": "attachment.schema.json",
    "type": "object",
    "additionalProperties": false,
    "properties": {
      "type": { "type": "string" },
      "image_url": { "type": "string", "format": "uri", "pattern": "^https://", "description": "Must be HTTPS and accessible" },
      "thumb_url": { "type": "string", "format": "uri", "pattern": "^https://", "description": "Must be HTTPS and accessible" },
      "asset_url": { "type": "string", "format": "uri", "pattern": "^https://", "description": "Must be HTTPS and accessible" },
      "migrate_resources": { "type": "boolean" }
    }
}
